setup.py
mydsnd_udacity/Binomialdistribution.py
mydsnd_udacity/Gaussiandistribution.py
mydsnd_udacity/Generaldistribution.py
mydsnd_udacity/__init__.py
mydsnd_udacity.egg-info/PKG-INFO
mydsnd_udacity.egg-info/SOURCES.txt
mydsnd_udacity.egg-info/dependency_links.txt
mydsnd_udacity.egg-info/not-zip-safe
mydsnd_udacity.egg-info/top_level.txt