Metadata-Version: 1.0
Name: mydsnd-udacity
Version: 1.0
Summary: Gaussian and Binomial distributions
Home-page: UNKNOWN
Author: ['Ante Kristic']
Author-email: UNKNOWN
License: UNKNOWN
Platform: UNKNOWN
